pulsefire/__init__.py
pulsefire/caches.py
pulsefire/clients.py
pulsefire/functools.py
pulsefire/invocation.py
pulsefire/middlewares.py
pulsefire/ratelimiters.py
pulsefire/schemas.py
pulsefire/taskgroups.py
pulsefire-2.0.30.dist-info/licenses/LICENSE
pulsefire-2.0.30.dist-info/METADATA
pulsefire-2.0.30.dist-info/WHEEL
pulsefire-2.0.30.dist-info/top_level.txt
pulsefire-2.0.30.dist-info/zip-safe
pulsefire-2.0.30.dist-info/RECORD
